sniperpy/__init__.py
sniperpy/smb_extractor.py
sniperpy-1.0.1.dist-info/METADATA
sniperpy-1.0.1.dist-info/WHEEL
sniperpy-1.0.1.dist-info/entry_points.txt
sniperpy-1.0.1.dist-info/top_level.txt
sniperpy-1.0.1.dist-info/RECORD
