Metadata-Version: 2.1
Name: sniperpy
Version: 1.0.1
Summary: A Python package to analyze SMB2 packets from pcap files
Home-page: https://github.com/powerexploit/sniper
Author: Ankit Dobhal
Author-email: dobhal.ankit@protonmail.com
Project-URL: Bug Tracker, https://github.com/powerexploit/sniper/issues
Classifier: Programming Language :: Python :: 3
Classifier: Operating System :: OS Independent
Requires-Python: >=3.6
Requires-Dist: scapy
